CHANGES.rst
MANIFEST.in
Manifest.in
README.rst
setup.cfg
setup.py
tox.ini
src/devpi_theme_16/.DS_Store
src/devpi_theme_16/__init__.py
src/devpi_theme_16/main.py
src/devpi_theme_16/views.py
src/devpi_theme_16.egg-info/PKG-INFO
src/devpi_theme_16.egg-info/SOURCES.txt
src/devpi_theme_16.egg-info/dependency_links.txt
src/devpi_theme_16.egg-info/entry_points.txt
src/devpi_theme_16.egg-info/not-zip-safe
src/devpi_theme_16.egg-info/requires.txt
src/devpi_theme_16.egg-info/top_level.txt
src/devpi_theme_16/theme/.DS_Store
src/devpi_theme_16/theme/static/style.css
src/devpi_theme_16/theme/static/css/16.css
src/devpi_theme_16/theme/static/css/16.css.map
src/devpi_theme_16/theme/static/css/16.scss
src/devpi_theme_16/theme/static/img/access_denied2.png
src/devpi_theme_16/theme/static/img/alert.png
src/devpi_theme_16/theme/static/img/icon-sprite.png
src/devpi_theme_16/theme/templates/doc.pt
src/devpi_theme_16/theme/templates/error.pt
src/devpi_theme_16/theme/templates/index.pt
src/devpi_theme_16/theme/templates/info.pt
src/devpi_theme_16/theme/templates/login.pt
src/devpi_theme_16/theme/templates/macros.pt
src/devpi_theme_16/theme/templates/notfound.pt
src/devpi_theme_16/theme/templates/project.pt
src/devpi_theme_16/theme/templates/remove.pt
src/devpi_theme_16/theme/templates/root.pt
src/devpi_theme_16/theme/templates/search.pt
src/devpi_theme_16/theme/templates/search_help.pt
src/devpi_theme_16/theme/templates/status.pt
src/devpi_theme_16/theme/templates/toxresult.pt
src/devpi_theme_16/theme/templates/toxresults.pt
src/devpi_theme_16/theme/templates/user.pt
src/devpi_theme_16/theme/templates/version.pt