Metadata-Version: 1.0
Name: devpi-theme-16
Version: 2.1.0
Summary: Theme plugin for devpi server
Home-page: UNKNOWN
Author: UNKNOWN
Author-email: UNKNOWN
License: MIT
Platform: UNKNOWN
